{
  "domain": {
    "id": "trees",
    "displayName": "Trees"
  },
  "analysisDate": "2025-09-01T12:22:03.341Z",
  "totalMunicipalitiesAnalyzed": 36,
  "averageScore": 1.84,
  "highestScoringMunicipality": {
    "id": "NY-SleepyHollow-Village",
    "displayName": "Sleepy Hollow - Village",
    "score": 4.16
  },
  "bestPractices": [
    {
      "questionId": 1,
      "question": "Do I need a permit to remove a tree on my private property, how do I apply, and who reviews it?",
      "bestAnswer": "Best practices include requiring a permit for the removal of trees on private property, particularly for trees over a specific diameter at breast height (e.g., 18 inches), those designated as protected or landmark, or located within sensitive areas such as scenic roads or steep slopes. The statute should mandate a detailed application process, including property and tree specifics, to be reviewed by an appropriate authority such as an Enforcement Officer or Planning Board. Exceptions may allow limited removal without a permit, such as up to three non-protected trees annually on smaller residential lots, ensuring a balance between property rights and environmental protection.",
      "bestScore": 1,
      "bestMunicipality": {
        "id": "NY-Ardsley-Village",
        "displayName": "Ardsley - Village"
      },
      "quantitativeHighlights": [],
      "supportingExamples": [
        {
          "municipality": {
            "id": "NY-Ardsley-Village",
            "displayName": "Ardsley - Village"
          },
          "score": 1,
          "confidence": 85
        },
        {
          "municipality": {
            "id": "NY-Bedford-Town",
            "displayName": "Bedford - Town"
          },
          "score": 1,
          "confidence": 85
        },
        {
          "municipality": {
            "id": "NY-BriarcliffManor-Village",
            "displayName": "Briarcliff Manor - Village"
          },
          "score": 1,
          "confidence": 85
        }
      ],
      "commonGaps": [
        "Permit process improvements",
        "Higher penalties needed",
        "Mandatory replacement standards"
      ]
    },
    {
      "questionId": 2,
      "question": "What are the penalties for removing trees without a permit?",
      "bestAnswer": "Best practices include requiring a permit for tree removal, with penalties for non-compliance such as fines up to $1,000 for first offenses and escalating fines for subsequent offenses. Each unlawfully removed tree should be treated as a separate offense, and additional penalties may include imprisonment up to 30 days or mandatory restoration and replanting of trees. The statute should also stipulate that no further permits, such as building permits or certificates of occupancy, will be issued until compliance with restoration requirements is verified.",
      "bestScore": 1,
      "bestMunicipality": {
        "id": "NY-Ardsley-Village",
        "displayName": "Ardsley - Village"
      },
      "quantitativeHighlights": [
        "Highest fine: $5,000",
        "Highest fine: $3,000",
        "Highest fine: $250"
      ],
      "supportingExamples": [
        {
          "municipality": {
            "id": "NY-Ardsley-Village",
            "displayName": "Ardsley - Village"
          },
          "score": 1,
          "confidence": 85
        },
        {
          "municipality": {
            "id": "NY-Bedford-Town",
            "displayName": "Bedford - Town"
          },
          "score": 1,
          "confidence": 85
        },
        {
          "municipality": {
            "id": "NY-BriarcliffManor-Village",
            "displayName": "Briarcliff Manor - Village"
          },
          "score": 1,
          "confidence": 85
        }
      ],
      "commonGaps": [
        "Permit process improvements",
        "Higher penalties needed",
        "Mandatory replacement standards"
      ]
    },
    {
      "questionId": 3,
      "question": "Are there fees associated with removing individual trees?",
      "bestAnswer": "Best practices include requiring a permit for tree removal on private property, with fees determined by a standardized fee schedule set by the governing body. The statute should require applicants to cover costs for professional assessments, such as hiring an ISA-certified arborist, when necessary for tree inventory or protection plans. Exemptions from fees should be considered for municipal projects to encourage public benefit initiatives.",
      "bestScore": 1,
      "bestMunicipality": {
        "id": "NY-Ardsley-Village",
        "displayName": "Ardsley - Village"
      },
      "quantitativeHighlights": [],
      "supportingExamples": [
        {
          "municipality": {
            "id": "NY-Ardsley-Village",
            "displayName": "Ardsley - Village"
          },
          "score": 1,
          "confidence": 85
        },
        {
          "municipality": {
            "id": "NY-Bedford-Town",
            "displayName": "Bedford - Town"
          },
          "score": 1,
          "confidence": 85
        },
        {
          "municipality": {
            "id": "NY-BriarcliffManor-Village",
            "displayName": "Briarcliff Manor - Village"
          },
          "score": 1,
          "confidence": 85
        }
      ],
      "commonGaps": [
        "Permit process improvements",
        "Enforcement mechanisms",
        "Higher penalties needed"
      ]
    },
    {
      "questionId": 4,
      "question": "Can I replant new trees to replace those removed, in lieu of a payment? Am I allowed to plant non-native species as replacements?",
      "bestAnswer": "Best practices include allowing the replanting of new trees as replacements for those removed, with a preference for native species to ensure ecological compatibility. The statute should require that replacement trees match the removed trees in species or follow an approved list, and that replanting plans be approved by a designated authority. Additionally, municipalities should mandate that if on-site replanting is impractical, a fee be paid into a dedicated tree fund, ensuring continued investment in urban forestry.",
      "bestScore": 1,
      "bestMunicipality": {
        "id": "NY-Ardsley-Village",
        "displayName": "Ardsley - Village"
      },
      "quantitativeHighlights": [],
      "supportingExamples": [
        {
          "municipality": {
            "id": "NY-Ardsley-Village",
            "displayName": "Ardsley - Village"
          },
          "score": 1,
          "confidence": 85
        },
        {
          "municipality": {
            "id": "NY-Bronxville-Village",
            "displayName": "Bronxville - Village"
          },
          "score": 1,
          "confidence": 85
        },
        {
          "municipality": {
            "id": "NY-Cortlandt-Town",
            "displayName": "Cortlandt - Town"
          },
          "score": 1,
          "confidence": 85
        }
      ],
      "commonGaps": [
        "Mandatory replacement standards",
        "Enforcement mechanisms",
        "Higher penalties needed"
      ]
    },
    {
      "questionId": 5,
      "question": "Which neighbors must be notified if I remove trees? ",
      "bestAnswer": "Best practices include requiring notification to all adjoining and directly opposite property owners, as well as those within a specified distance (e.g., 50 yards or 300 feet) of the tree in question. The statute should mandate that this notification be sent via certified mail, return receipt requested, at least 15 days before any decision or public hearing on the tree removal application. Additionally, a permit sign should be publicly posted on-site, clearly visible from the street, at least three days before tree removal begins to ensure community awareness.",
      "bestScore": 1,
      "bestMunicipality": {
        "id": "NY-BriarcliffManor-Village",
        "displayName": "Briarcliff Manor - Village"
      },
      "quantitativeHighlights": [],
      "supportingExamples": [
        {
          "municipality": {
            "id": "NY-BriarcliffManor-Village",
            "displayName": "Briarcliff Manor - Village"
          },
          "score": 1,
          "confidence": 85
        },
        {
          "municipality": {
            "id": "NY-Cortlandt-Town",
            "displayName": "Cortlandt - Town"
          },
          "score": 1,
          "confidence": 85
        },
        {
          "municipality": {
            "id": "NY-DobbsFerry-Village",
            "displayName": "Dobbs Ferry - Village"
          },
          "score": 1,
          "confidence": 85
        }
      ],
      "commonGaps": [
        "Neighbor notification requirements",
        "Permit process improvements"
      ]
    },
    {
      "questionId": 6,
      "question": "Does the code recognize the importance of keeping a healthy tree canopy?",
      "bestAnswer": "Best practices for maintaining a healthy tree canopy include requiring permits for tree removal and imposing restrictions on harmful activities such as tree topping. The statute should mandate the preservation of diverse tree species and ages, encourage replanting efforts, and establish penalties for non-compliance to prevent indiscriminate tree damage. Additionally, it should emphasize the ecological benefits of trees, such as soil stabilization and air quality improvement, to ensure long-term community welfare.",
      "bestScore": 1,
      "bestMunicipality": {
        "id": "NY-Cortlandt-Town",
        "displayName": "Cortlandt - Town"
      },
      "quantitativeHighlights": [],
      "supportingExamples": [
        {
          "municipality": {
            "id": "NY-Cortlandt-Town",
            "displayName": "Cortlandt - Town"
          },
          "score": 1,
          "confidence": 85
        },
        {
          "municipality": {
            "id": "NY-Croton-on-Hudson-Village",
            "displayName": "Croton-on-Hudson - Village"
          },
          "score": 1,
          "confidence": 85
        },
        {
          "municipality": {
            "id": "NY-DobbsFerry-Village",
            "displayName": "Dobbs Ferry - Village"
          },
          "score": 1,
          "confidence": 85
        }
      ],
      "commonGaps": [
        "Mandatory replacement standards",
        "Enforcement mechanisms",
        "Higher penalties needed"
      ]
    },
    {
      "questionId": 8,
      "question": "What are my responsibilities for maintaining trees on my property?",
      "bestAnswer": "Best practices for maintaining trees on private property should require property owners to ensure that trees do not overhang public streets or sidewalks below specified heights (e.g., 15 feet above roads and 9 feet above sidewalks) and to remove dead or hazardous trees promptly. The statute should mandate permits for the removal of significant trees, with conditions for replanting to mitigate environmental impacts. Additionally, property owners should be responsible for regular maintenance, such as trimming and pruning, and must restore areas and replant trees if removal occurs without proper permissions.",
      "bestScore": 1,
      "bestMunicipality": {
        "id": "NY-Ardsley-Village",
        "displayName": "Ardsley - Village"
      },
      "quantitativeHighlights": [],
      "supportingExamples": [
        {
          "municipality": {
            "id": "NY-Ardsley-Village",
            "displayName": "Ardsley - Village"
          },
          "score": 1,
          "confidence": 85
        },
        {
          "municipality": {
            "id": "NY-Bedford-Town",
            "displayName": "Bedford - Town"
          },
          "score": 1,
          "confidence": 85
        },
        {
          "municipality": {
            "id": "NY-BriarcliffManor-Village",
            "displayName": "Briarcliff Manor - Village"
          },
          "score": 1,
          "confidence": 85
        }
      ],
      "commonGaps": [
        "Higher penalties needed",
        "Permit process improvements",
        "Enforcement mechanisms"
      ]
    },
    {
      "questionId": 9,
      "question": "Does the statute call for data collection on tree removals and presentation in a report to the public?",
      "bestAnswer": "The statute should require the establishment of a Tree Advisory Board or equivalent body responsible for advising on tree preservation and removal, with a mandate to produce an annual report to the governing body. This report should include data collection on tree removals, an inventory of significant trees, and a community forestry work plan, which should be made publicly accessible. Additionally, documentation related to tree removals, such as arborist reports and test results, should be maintained and available upon request to ensure transparency and informed decision-making.",
      "bestScore": 1,
      "bestMunicipality": {
        "id": "NY-Scarsdale-Town",
        "displayName": "Scarsdale - Town"
      },
      "quantitativeHighlights": [],
      "supportingExamples": [
        {
          "municipality": {
            "id": "NY-Scarsdale-Town",
            "displayName": "Scarsdale - Town"
          },
          "score": 1,
          "confidence": 85
        },
        {
          "municipality": {
            "id": "NY-Bedford-Town",
            "displayName": "Bedford - Town"
          },
          "score": 0.95,
          "confidence": 85
        },
        {
          "municipality": {
            "id": "NY-Cortlandt-Town",
            "displayName": "Cortlandt - Town"
          },
          "score": 0.95,
          "confidence": 85
        }
      ],
      "commonGaps": [
        "Mandatory replacement standards",
        "Professional consultation required",
        "Higher penalties needed"
      ]
    }
  ],
  "overallRecommendations": {
    "commonWeaknesses": [],
    "keyImprovements": [
      "Permit process improvements",
      "Higher penalties needed",
      "Mandatory replacement standards",
      "Enforcement mechanisms",
      "Neighbor notification requirements",
      "Professional consultation required"
    ],
    "modelMunicipalities": [
      "Sleepy Hollow - Village",
      "New Rochelle - City",
      "New Castle - Town",
      "Ossining - Town",
      "Yorktown - Town"
    ]
  },
  "version": "1.0"
}